era5dl/__init__.py
era5dl/util_downloader.py
era5dl/util_general.py
era5dl/util_read_param_table.py
era5dl/util_request_parser.py
era5dl/examples/__init__.py
era5dl/examples/batch_download.py
era5dl/examples/era5_downloader.log
era5dl/examples/simple_download.py
era5dl/examples/split_web_api_request.py
era5dl/examples/test_api1.txt
era5dl/tables/table1.csv
era5dl/tables/table10.csv
era5dl/tables/table11.csv
era5dl/tables/table12.csv
era5dl/tables/table13.csv
era5dl/tables/table1b.csv
era5dl/tables/table2.csv
era5dl/tables/table3.csv
era5dl/tables/table4.csv
era5dl/tables/table5.csv
era5dl/tables/table6.csv
era5dl/tables/table7.csv
era5dl/tables/table8.csv
era5dl/tables/table9.csv
era5_dl-0.1a1.dist-info/LICENSE
era5_dl-0.1a1.dist-info/METADATA
era5_dl-0.1a1.dist-info/WHEEL
era5_dl-0.1a1.dist-info/top_level.txt
era5_dl-0.1a1.dist-info/RECORD
