Metadata-Version: 2.1
Name: era5-dl
Version: 0.1a1
Summary: a simple helper for downloading ECMWF's ERA5 reanalysis data
Home-page: https://github.com/Xunius/era5-dl
Author: Guangzhi XU
Author-email: xugzhi1987@gmail.com
License: UNKNOWN
Platform: UNKNOWN
Classifier: Development Status :: 3 - Alpha
Classifier: Environment :: Console
Classifier: Intended Audience :: End Users/Desktop
Classifier: License :: OSI Approved :: GNU General Public License v3 (GPLv3)
Classifier: Natural Language :: English
Classifier: Operating System :: POSIX :: Linux
Classifier: Operating System :: MacOS
Classifier: Operating System :: Microsoft
Classifier: Programming Language :: Python :: 3
Classifier: Topic :: Education
Requires-Python: >=3
Requires-Dist: cdsapi
